{"result":{"status":"200","message":""},"data":[{"id":1401,"nickname":"whateverghost","webtoonType":"series","title":"귀신이면 어때","finishYn":"N","thumbnailImage2":{"id":0,"url":"http://t1.daumcdn.net/webtoon/op/a5ecbd59cc2d2bec60bab8455a146c4c1f72840a","width":0,"height":0,"serviceStatus":"service"},"appThumbnailImage":{"id":0,"url":"http://t1.daumcdn.net/webtoon/op/f3d68349cd3a951901063d0e0db7cdeba9b6eea6","width":0,"height":0,"serviceStatus":"service"},"pcThumbnailImage":{"id":0,"url":"http://t1.daumcdn.net/webtoon/op/c911a14697108a3134704e5ee38f443cc43e2bef","width":0,"height":0,"serviceStatus":"service"},"pcRecommendImage":{"id":0,"url":"http://t1.daumcdn.net/webtoon/op/dceb52e57257e63e0b8c71938f5534670269a93b","width":0,"height":0,"serviceStatus":"service"},"pcHomeImage":{"id":0,"url":"http://t1.daumcdn.net/webtoon/op/bca44b0b682a742ee206e53ea58c790237a0a6da","width":0,"height":0,"serviceStatus":"service"},"pcHomeRightImage":{"id":0,"url":"http://t1.daumcdn.net/webtoon/op/bf3f584f4af3a56aca5369512739b232a1898c52","width":0,"height":0,"serviceStatus":"service"},"pcHomeLeftColor":"7e5a88","pcHomeRightColor":"7e5a88","introduction":"취준생과 처녀 귀신의 대책 없는 낭만 로맨스!","startDate":"20171121000000","serviceStatus":"service","viewerType":"scroll","weekTerm":"weekly","articleId":0,"media":"daum","payYn":"N","payType":"free","price":0,"ageGrade":0,"restYn":"N","monopolize":"N","dateCreated":"20171117110624","webtoonComment":{"id":0,"articleId":1401,"commentUseYn":"N"},"cartoon":{"id":62581,"genres":[{"id":4,"name":"판타지"},{"id":5,"name":"순정"}],"artists":[{"id":27669,"name":"규규","penName":"규규","email":"","homepage":"","artistOrder":0,"artistType":"picture"},{"id":27669,"name":"규규","penName":"규규","email":"","homepage":"","artistOrder":0,"artistType":"story"}],"categories":[{"id":80,"name":"귀신","categoryType":"keyword","priority":1},{"id":241,"name":"설화","categoryType":"keyword","priority":2},{"id":310,"name":"연애","categoryType":"keyword","priority":2},{"id":380,"name":"저승","categoryType":"keyword","priority":2},{"id":1,"name":"스토리","categoryType":"story","priority":0}]},"webtoonWeeks":[{"id":20069,"weekDay":"tue"}],"latestWebtoonEpisode":{"id":46491,"episode":4,"title":"3화 생존게임","thumbnailImage":{"id":46491,"url":"http://t1.daumcdn.net/cartoon/5A1B7C480103720001","width":0,"height":0,"serviceStatus":"service"},"episodeImage":{"id":0,"url":"http://t1.daumcdn.net/cartoon/5A1B7C9E055B9D0001","width":0,"height":0,"serviceStatus":"service"},"encryptUseYn":"N","serviceStatus":"service","articleId":0,"dateCreated":"20171212000100","price":0,"isTopRecommend":false,"isPaid":false,"ticketAvailable":false},"webtoonServices":[{"id":35054,"webtoonId":1401,"serviceTarget":"series"},{"id":35055,"webtoonId":1401,"serviceTarget":"padtoon"},{"id":35056,"webtoonId":1401,"serviceTarget":"mobile"},{"id":35057,"webtoonId":1401,"serviceTarget":"app"}],"score":0.0,"isNew":true,"averageScore":9.886572143452877,"ranking":0,"diff":0,"metricsScore":0,"sort":"desc","sortWeight":1},{"id":1395,"nickname":"Matchless","webtoonType":"series","title":"아비무쌍","finishYn":"N","thumbnailImage2":{"id":0,"url":"http://t1.daumcdn.net/webtoon/op/6d9218f2cde432dc5fff8d5e1ffe6cf20b6f89d9","width":0,"height":0,"serviceStatus":"service"},"appThumbnailImage":{"id":0,"url":"http://t1.daumcdn.net/webtoon/op/3492bbf9a30176ff0778931e0e9b92d715930a65","width":0,"height":0,"serviceStatus":"service"},"pcThumbnailImage":{"id":0,"url":"http://t1.daumcdn.net/webtoon/op/49bb2a8f72c35ae85af3bb6193cf59ab5db53c2a","width":0,"height":0,"serviceStatus":"service"},"pcRecommendImage":{"id":0,"url":"http://t1.daumcdn.net/webtoon/op/1ce3a2fedeec309e0a6415c1a47f5301768e3552","width":0,"height":0,"serviceStatus":"service"},"pcHomeImage":{"id":0,"url":"http://t1.daumcdn.net/webtoon/op/0410ba90bf883cf29542477f50600a65b47a2fbe","width":0,"height":0,"serviceStatus":"service"},"pcHomeRightImage":{"id":0,"url":"http://t1.daumcdn.net/webtoon/op/be5991caef535c1ee581521d1c63abf655890197","width":0,"height":0,"serviceStatus":"service"},"pcHomeLeftColor":"c79267","pcHomeRightColor":"c79267","introduction":"하늘의 뜻을 아니 아비는 무쌍이다. \u0027레드스톰\u0027 노경찬 작가의 신작","startDate":"20171024000000","serviceStatus":"service","viewerType":"scroll","weekTerm":"weekly","articleId":0,"media":"daum","payYn":"N","payType":"free","price":0,"ageGrade":0,"restYn":"N","monopolize":"N","dateCreated":"20171023165309","webtoonComment":{"id":0,"articleId":1395,"commentUseYn":"N"},"cartoon":{"id":62410,"genres":[{"id":4,"name":"판타지"},{"id":7,"name":"무협"}],"artists":[{"id":27584,"name":"이현석","penName":"이현석","email":"","homepage":"","artistOrder":0,"artistType":"picture"},{"id":14092,"name":"노경찬","penName":"노경찬","nameImage":{"id":39689105,"url":"http://i1.cartoon.daumcdn.net/svc/image/U03/cartoon/4F386E900151470002","width":0,"height":0,"serviceStatus":"service"},"debutDay":"20120121000000","teamYn":"N","artistOrder":1,"artistType":"story"}],"categories":[{"id":170,"name":"무장","categoryType":"keyword","priority":1},{"id":243,"name":"성장드라마","categoryType":"keyword","priority":2},{"id":290,"name":"아빠","categoryType":"keyword","priority":2},{"id":315,"name":"영웅","categoryType":"keyword","priority":2},{"id":1,"name":"스토리","categoryType":"story","priority":0}]},"webtoonWeeks":[{"id":20061,"weekDay":"tue"}],"latestWebtoonEpisode":{"id":46332,"episode":8,"title":"7화","thumbnailImage":{"id":46332,"url":"http://t1.daumcdn.net/cartoon/59F5F64B0220880002","width":0,"height":0,"serviceStatus":"service"},"episodeImage":{"id":0,"url":"http://t1.daumcdn.net/cartoon/59F5F64E01775F0001","width":0,"height":0,"serviceStatus":"service"},"encryptUseYn":"N","serviceStatus":"service","articleId":0,"dateCreated":"20171212000100","price":0,"isTopRecommend":false,"isPaid":false,"ticketAvailable":false},"webtoonServices":[{"id":35030,"webtoonId":1395,"serviceTarget":"series"},{"id":35031,"webtoonId":1395,"serviceTarget":"padtoon"},{"id":35032,"webtoonId":1395,"serviceTarget":"mobile"},{"id":35033,"webtoonId":1395,"serviceTarget":"app"}],"score":0.0,"isNew":true,"averageScore":9.934060721062618,"ranking":0,"diff":0,"metricsScore":0,"sort":"desc","sortWeight":0},{"id":1369,"nickname":"hellTemple","webtoonType":"series","title":"지옥사원","finishYn":"N","thumbnailImage":{"id":0,"url":"http://t1.daumcdn.net/cartoon/592BE5740212600001","width":0,"height":0,"serviceStatus":"service"},"thumbnailImage2":{"id":0,"url":"http://t1.daumcdn.net/webtoon/op/d8d45167e179120963d70ca2d19833f07342dfd7","width":0,"height":0,"serviceStatus":"service"},"padThumbnailImage":{"id":0,"url":"http://t1.daumcdn.net/cartoon/592BE5820515760001","width":0,"height":0,"serviceStatus":"service"},"homeThumbnailImage":{"id":0,"url":"http://t1.daumcdn.net/cartoon/592BE57B0246E60001","width":0,"height":0,"serviceStatus":"service"},"appThumbnailImage":{"id":0,"url":"http://t1.daumcdn.net/webtoon/op/281fc5b4a7cfbd7a56477297b091d9d9d30cde8b","width":0,"height":0,"serviceStatus":"service"},"pcThumbnailImage":{"id":0,"url":"http://t1.daumcdn.net/webtoon/op/17b38f55433209c0d858f7a96001f8d2ca287dba","width":0,"height":0,"serviceStatus":"service"},"pcRecommendImage":{"id":0,"url":"http://t1.daumcdn.net/webtoon/op/5fdf137590afac7768a9f87f57454f5e63cfd000","width":0,"height":0,"serviceStatus":"service"},"pcHomeImage":{"id":0,"url":"http://t1.daumcdn.net/webtoon/op/9e7f702f04c82e7f5c32ce5ee060b8a4723b1abb","width":0,"height":0,"serviceStatus":"service"},"pcHomeRightImage":{"id":0,"url":"http://t1.daumcdn.net/webtoon/op/a4a6941022d7c454d3ed5073a4243f15370fbdf6","width":0,"height":0,"serviceStatus":"service"},"pcHomeLeftColor":"bf8578","pcHomeRightColor":"bf8578","introduction":"인간이 된 악마의 사회 적응기! 그리고 그를 위협하는 존재들. 캐러멜, 네온비의 개성 강한 신작!","startDate":"20170530000000","serviceStatus":"service","viewerType":"scroll","weekTerm":"weekly","articleId":0,"media":"daum","payYn":"N","payType":"free","price":0,"ageGrade":0,"restYn":"N","monopolize":"N","dateCreated":"20170529154403","webtoonComment":{"id":0,"articleId":1369,"commentUseYn":"N"},"cartoon":{"id":61454,"genres":[{"id":2,"name":"드라마"},{"id":4,"name":"판타지"}],"artists":[{"id":80,"name":"캐러멜","penName":"캐러멜","history":"\u003cp\u003e2005년 남아돌아 \u003cbr /\u003e\r\n2006년 오리우리 \u003cbr /\u003e\r\n2007년 미스문방구 매니저\u003cbr /\u003e\r\n2010년 셔틀맨\u003cbr /\u003e\r\n2011년 다이어터\u003c/p\u003e","smallPictureImage":{"id":58483,"url":"http://i1.cartoon.daumcdn.net/svc/image/U03/cartoon/U23830264AA07C7622","width":0,"height":0,"serviceStatus":"service"},"appImage":{"id":44856221,"url":"http://i1.cartoon.daumcdn.net/svc/image/U03/cartoon/519477510601960005","width":0,"height":0,"serviceStatus":"service"},"nameImage":{"id":6948038,"url":"http://i1.cartoon.daumcdn.net/svc/image/U03/cartoon/U544C0049A96A43D46","width":0,"height":0,"serviceStatus":"service"},"birthDay":"19820818000000","debutDay":"20050818000000","email":"ohdzang@hanmail.net","homepage":"","blog":"http://blog.naver.com/ohdzang.do","fancafe":"http://cafe.daum.net/MISSmm","twitter":"https://twitter.com/1982caramel","teamYn":"N","artistOrder":0,"artistType":"picture"},{"id":11653,"name":"네온비","penName":"네온비","history":"\u003cp\u003e 2007년 \u003c팝툰\u003e 단편으로 데뷔 \u003cbr /\u003e\r\n2008년 \u003c미스문방구매니저\u003e  배경/채색/공동시나리오 \u003cbr /\u003e\r\n2010년 \u003c셔틀맨\u003e - 스토리작가 \u003cbr /\u003e\r\n2011년 \u003c다이어터\u003e - 스토리작가 \u003cbr /\u003e\r\n2011년 \u003c기춘씨에게도 봄은 오는가\u003e \u003cbr /\u003e\r\n기타 광고카툰, 학습만화 다수\u003c/p\u003e","smallPictureImage":{"id":30306857,"url":"http://i1.cartoon.daumcdn.net/svc/image/U03/cartoon/U731B73B4DAF7E1A36","width":0,"height":0,"serviceStatus":"service"},"appImage":{"id":44855701,"url":"http://i1.cartoon.daumcdn.net/svc/image/U03/cartoon/5194705C041D260005","width":0,"height":0,"serviceStatus":"service"},"nameImage":{"id":30306858,"url":"http://i1.cartoon.daumcdn.net/svc/image/U03/cartoon/U539EF5475856B6304","width":0,"height":0,"serviceStatus":"service"},"birthDay":"19850725000000","debutDay":"20070101000000","email":"neonbcartoon@hanmail.net","blog":"http://neonb.net","fancafe":"http://cafe.daum.net/MISSmm","teamYn":"N","artistOrder":1,"artistType":"story"}],"categories":[{"id":295,"name":"악마","categoryType":"keyword","priority":1},{"id":380,"name":"저승","categoryType":"keyword","priority":2},{"id":507,"name":"빙의","categoryType":"keyword","priority":2},{"id":347,"name":"음식","categoryType":"keyword","priority":2},{"id":1,"name":"스토리","categoryType":"story","priority":1}]},"webtoonWeeks":[{"id":19929,"weekDay":"tue"}],"latestWebtoonEpisode":{"id":46329,"episode":29,"title":"28화","thumbnailImage":{"id":46329,"url":"http://t1.daumcdn.net/cartoon/5A124282010CB70001","width":0,"height":0,"serviceStatus":"service"},"episodeImage":{"id":0,"url":"http://t1.daumcdn.net/cartoon/5A124285057A0F0002","width":0,"height":0,"serviceStatus":"service"},"encryptUseYn":"N","serviceStatus":"service","articleId":0,"dateCreated":"20171212000100","price":0,"isTopRecommend":false,"isPaid":false,"ticketAvailable":false},"webtoonServices":[{"id":34520,"webtoonId":1369,"serviceTarget":"series"},{"id":34521,"webtoonId":1369,"serviceTarget":"padtoon"},{"id":34522,"webtoonId":1369,"serviceTarget":"mobile"},{"id":34523,"webtoonId":1369,"serviceTarget":"app"}],"score":0.0,"isNew":false,"averageScore":9.816933169331694,"ranking":0,"diff":0,"metricsScore":0,"sort":"desc","sortWeight":0},{"id":1359,"nickname":"PrejudiceLove","webtoonType":"series","title":"오만상과 편견","finishYn":"N","thumbnailImage":{"id":0,"url":"http://t1.daumcdn.net/cartoon/58F4466C0375D60001","width":0,"height":0,"serviceStatus":"service"},"thumbnailImage2":{"id":0,"url":"http://t1.daumcdn.net/cartoon/58F44666022CD60002","width":0,"height":0,"serviceStatus":"service"},"padThumbnailImage":{"id":0,"url":"http://t1.daumcdn.net/cartoon/58F446800235E00001","width":0,"height":0,"serviceStatus":"service"},"homeThumbnailImage":{"id":0,"url":"http://t1.daumcdn.net/cartoon/58F4467A0231BB0001","width":0,"height":0,"serviceStatus":"service"},"appThumbnailImage":{"id":0,"url":"http://t1.daumcdn.net/cartoon/5922A8910202BE0002","width":0,"height":0,"serviceStatus":"service"},"pcThumbnailImage":{"id":0,"url":"http://t1.daumcdn.net/cartoon/58F4E8A90433290001","width":0,"height":0,"serviceStatus":"service"},"pcRecommendImage":{"id":0,"url":"http://t1.daumcdn.net/webtoon/op/79da518c3c22e12a6274a925d958a69e9476f2d0","width":0,"height":0,"serviceStatus":"service"},"pcHomeImage":{"id":0,"url":"http://t1.daumcdn.net/cartoon/58F4469B067D5A0001","width":0,"height":0,"serviceStatus":"service"},"pcHomeRightImage":{"id":0,"url":"http://t1.daumcdn.net/cartoon/58F4E70B052E110002","width":0,"height":0,"serviceStatus":"service"},"pcHomeLeftColor":"7374a6","pcHomeRightColor":"7374a6","introduction":"매 순간마다 오해와 편견으로 부딪히는 남녀의 로맨스!","startDate":"20170418000000","serviceStatus":"service","viewerType":"scroll","weekTerm":"weekly","articleId":0,"media":"daum","payYn":"N","payType":"free","price":0,"ageGrade":0,"restYn":"N","monopolize":"N","dateCreated":"20170417133847","webtoonComment":{"id":0,"articleId":1359,"commentUseYn":"N"},"cartoon":{"id":61218,"genres":[{"id":2,"name":"드라마"},{"id":5,"name":"순정"}],"artists":[{"id":138,"name":"유현숙","penName":"유현숙","introduction":"1997년 윙크 공모전에 \u003cDream\u003e을 발표하며 데뷔. 코믹한 장르에 탁월한 실력을 발휘하여 \u003c연애 다이어리\u003e \u003c러브 미\u003e 등의 로맨스 코믹 작품을 발표. 현재 잡지 ‘파티’에 \u003c새나에게 사랑을\u003e 연재 중.","smallPictureImage":{"id":26012744,"url":"http://i1.cartoon.daumcdn.net/svc/image/U03/cartoon/4E0043AD051E020001","width":0,"height":0,"serviceStatus":"service"},"appImage":{"id":44499547,"url":"http://i1.cartoon.daumcdn.net/svc/image/U03/cartoon/517765E3053BFF0001","width":0,"height":0,"serviceStatus":"service"},"nameImage":{"id":6948094,"url":"http://i1.cartoon.daumcdn.net/svc/image/U03/cartoon/U644C0049A96D62C7E","width":0,"height":0,"serviceStatus":"service"},"debutDay":"19970917000000","homepage":"","teamYn":"N","artistOrder":0,"artistType":"picture"},{"id":138,"name":"유현숙","penName":"유현숙","introduction":"1997년 윙크 공모전에 \u003cDream\u003e을 발표하며 데뷔. 코믹한 장르에 탁월한 실력을 발휘하여 \u003c연애 다이어리\u003e \u003c러브 미\u003e 등의 로맨스 코믹 작품을 발표. 현재 잡지 ‘파티’에 \u003c새나에게 사랑을\u003e 연재 중.","smallPictureImage":{"id":26012744,"url":"http://i1.cartoon.daumcdn.net/svc/image/U03/cartoon/4E0043AD051E020001","width":0,"height":0,"serviceStatus":"service"},"appImage":{"id":44499547,"url":"http://i1.cartoon.daumcdn.net/svc/image/U03/cartoon/517765E3053BFF0001","width":0,"height":0,"serviceStatus":"service"},"nameImage":{"id":6948094,"url":"http://i1.cartoon.daumcdn.net/svc/image/U03/cartoon/U644C0049A96D62C7E","width":0,"height":0,"serviceStatus":"service"},"debutDay":"19970917000000","homepage":"","teamYn":"N","artistOrder":0,"artistType":"story"}],"categories":[{"id":310,"name":"연애","categoryType":"keyword","priority":1},{"id":210,"name":"사랑","categoryType":"keyword","priority":2},{"id":208,"name":"사건사고","categoryType":"keyword","priority":2},{"id":418,"name":"짝사랑","categoryType":"keyword","priority":2},{"id":1,"name":"스토리","categoryType":"story","priority":1}]},"webtoonWeeks":[{"id":19897,"weekDay":"tue"}],"latestWebtoonEpisode":{"id":46113,"episode":34,"title":"33화 모순","thumbnailImage":{"id":46113,"url":"http://t1.daumcdn.net/cartoon/5A0902B80209590001","width":0,"height":0,"serviceStatus":"service"},"episodeImage":{"id":0,"url":"http://t1.daumcdn.net/cartoon/5A0902BC0670330001","width":0,"height":0,"serviceStatus":"service"},"encryptUseYn":"N","serviceStatus":"service","articleId":0,"dateCreated":"20171212000100","price":0,"isTopRecommend":false,"isPaid":false,"ticketAvailable":false},"webtoonServices":[{"id":34396,"webtoonId":1359,"serviceTarget":"series"},{"id":34397,"webtoonId":1359,"serviceTarget":"padtoon"},{"id":34398,"webtoonId":1359,"serviceTarget":"mobile"},{"id":34399,"webtoonId":1359,"serviceTarget":"app"}],"score":0.0,"isNew":false,"averageScore":9.817133874770763,"ranking":0,"diff":0,"metricsScore":0,"sort":"desc","sortWeight":0},{"id":1352,"nickname":"TwentyReport","webtoonType":"series","title":"20세 보고서","finishYn":"N","titleImage2":{"id":0,"url":"http://t1.daumcdn.net/cartoon/58B3E7B8032A240002","width":0,"height":0,"serviceStatus":"service"},"thumbnailImage":{"id":0,"url":"http://t1.daumcdn.net/cartoon/58AA9BD302214E0001","width":0,"height":0,"serviceStatus":"service"},"thumbnailImage2":{"id":0,"url":"http://t1.daumcdn.net/cartoon/58AA9BCC0275F30003","width":0,"height":0,"serviceStatus":"service"},"padThumbnailImage":{"id":0,"url":"http://t1.daumcdn.net/cartoon/58AA9BDF0679FB0001","width":0,"height":0,"serviceStatus":"service"},"homeThumbnailImage":{"id":0,"url":"http://t1.daumcdn.net/cartoon/58AA9BD9065D2A0002","width":0,"height":0,"serviceStatus":"service"},"appThumbnailImage":{"id":0,"url":"http://t1.daumcdn.net/cartoon/58AA9BE6043DEE0006","width":0,"height":0,"serviceStatus":"service"},"pcThumbnailImage":{"id":0,"url":"http://t1.daumcdn.net/cartoon/58AA9BEF0233AE0001","width":0,"height":0,"serviceStatus":"service"},"pcRecommendImage":{"id":0,"url":"http://t1.daumcdn.net/webtoon/op/b55a4338f3aed112265ea00da1dda5c911e44449","width":0,"height":0,"serviceStatus":"service"},"pcHomeImage":{"id":0,"url":"http://t1.daumcdn.net/cartoon/58AA9C050544BF0001","width":0,"height":0,"serviceStatus":"service"},"pcHomeRightImage":{"id":0,"url":"http://t1.daumcdn.net/cartoon/58AA9C0C0409C20001","width":0,"height":0,"serviceStatus":"service"},"pcHomeLeftColor":"eb9483","pcHomeRightColor":"eb9483","introduction":"이제 막 성인이 된 초보 20세들의 이야기","startDate":"20170221000000","serviceStatus":"service","viewerType":"scroll","weekTerm":"weekly","articleId":0,"media":"daum","payYn":"N","payType":"free","price":0,"ageGrade":0,"restYn":"N","monopolize":"N","dateCreated":"20170220163521","webtoonComment":{"id":0,"articleId":1352,"commentUseYn":"N"},"cartoon":{"id":60817,"genres":[{"id":2,"name":"드라마"}],"artists":[{"id":26672,"name":"YSE","penName":"YSE","nameImage":{"id":55149592,"url":"http://t1.daumcdn.net/cartoon/58A56A140245E70001","width":0,"height":0,"serviceStatus":"service"},"debutDay":"20170221000000","teamYn":"N","artistOrder":1,"artistType":"picture"},{"id":26672,"name":"YSE","penName":"YSE","nameImage":{"id":55149592,"url":"http://t1.daumcdn.net/cartoon/58A56A140245E70001","width":0,"height":0,"serviceStatus":"service"},"debutDay":"20170221000000","teamYn":"N","artistOrder":1,"artistType":"story"}],"categories":[{"id":464,"name":"학교생활","categoryType":"keyword","priority":1},{"id":436,"name":"친구","categoryType":"keyword","priority":2},{"id":243,"name":"성장드라마","categoryType":"keyword","priority":2},{"id":111,"name":"대학생","categoryType":"keyword","priority":2},{"id":1,"name":"스토리","categoryType":"story","priority":0}]},"webtoonWeeks":[{"id":19659,"weekDay":"tue"}],"latestWebtoonEpisode":{"id":46496,"episode":35,"title":"33화","thumbnailImage":{"id":46496,"url":"http://t1.daumcdn.net/cartoon/5A197D56021B830001","width":0,"height":0,"serviceStatus":"service"},"episodeImage":{"id":0,"url":"http://t1.daumcdn.net/cartoon/5A197D590227450001","width":0,"height":0,"serviceStatus":"service"},"encryptUseYn":"N","serviceStatus":"service","articleId":0,"dateCreated":"20171212000100","price":0,"isTopRecommend":false,"isPaid":false,"ticketAvailable":false},"webtoonServices":[{"id":33556,"webtoonId":1352,"serviceTarget":"series"},{"id":33557,"webtoonId":1352,"serviceTarget":"padtoon"},{"id":33558,"webtoonId":1352,"serviceTarget":"mobile"},{"id":33559,"webtoonId":1352,"serviceTarget":"app"}],"score":0.0,"isNew":false,"averageScore":9.713225806451613,"ranking":0,"diff":0,"metricsScore":0,"sort":"desc","sortWeight":1},{"id":1349,"nickname":"AnOutcast","webtoonType":"series","title":"개밥도토리","finishYn":"N","titleImage2":{"id":0,"url":"http://t1.daumcdn.net/cartoon/58A25BB804491A0001","width":0,"height":0,"serviceStatus":"service"},"thumbnailImage":{"id":0,"url":"http://t1.daumcdn.net/cartoon/58A157F10660A40001","width":0,"height":0,"serviceStatus":"service"},"thumbnailImage2":{"id":0,"url":"http://t1.daumcdn.net/cartoon/58A189020221130003","width":0,"height":0,"serviceStatus":"service"},"padThumbnailImage":{"id":0,"url":"http://t1.daumcdn.net/cartoon/58A157FF06381F0001","width":0,"height":0,"serviceStatus":"service"},"homeThumbnailImage":{"id":0,"url":"http://t1.daumcdn.net/cartoon/58A157F802321D0001","width":0,"height":0,"serviceStatus":"service"},"appThumbnailImage":{"id":0,"url":"http://t1.daumcdn.net/cartoon/58A1580B0522CD0001","width":0,"height":0,"serviceStatus":"service"},"pcThumbnailImage":{"id":0,"url":"http://t1.daumcdn.net/cartoon/58A25BB402758D0001","width":0,"height":0,"serviceStatus":"service"},"pcRecommendImage":{"id":0,"url":"http://t1.daumcdn.net/webtoon/op/1ae7d458a613e4e2a8764009dff30fb7b41d1e24","width":0,"height":0,"serviceStatus":"service"},"pcHomeImage":{"id":0,"url":"http://t1.daumcdn.net/cartoon/58A1590B061CED0001","width":0,"height":0,"serviceStatus":"service"},"pcHomeRightImage":{"id":0,"url":"http://t1.daumcdn.net/cartoon/58A159120376410002","width":0,"height":0,"serviceStatus":"service"},"pcHomeLeftColor":"c19298","pcHomeRightColor":"c19298","introduction":"갑자기 개가 된 조영수. 개인 듯 개 아닌 개 같은 그의 이야기.","startDate":"20170214000000","serviceStatus":"service","viewerType":"scroll","weekTerm":"weekly","articleId":0,"media":"daum","payYn":"N","payType":"free","price":0,"ageGrade":0,"restYn":"N","monopolize":"N","dateCreated":"20170213155900","webtoonComment":{"id":0,"articleId":1349,"commentUseYn":"N"},"cartoon":{"id":60771,"genres":[{"id":2,"name":"드라마"},{"id":6,"name":"코믹"}],"artists":[{"id":26652,"name":"망기","penName":"망기","introduction":"잘 부탁드립니다 :)","nameImage":{"id":55138898,"url":"http://t1.daumcdn.net/cartoon/58A133100278D80002","width":0,"height":0,"serviceStatus":"service"},"debutDay":"20170214000000","email":"mang8907@gmail.com","homepage":"","teamYn":"N","artistOrder":1,"artistType":"picture"},{"id":26653,"name":"호형","penName":"호형","nameImage":{"id":55138899,"url":"http://t1.daumcdn.net/cartoon/58A1331C0151320001","width":0,"height":0,"serviceStatus":"service"},"debutDay":"20170214000000","teamYn":"N","artistOrder":1,"artistType":"story"}],"categories":[{"id":42,"name":"강아지","categoryType":"keyword","priority":1},{"id":310,"name":"연애","categoryType":"keyword","priority":2},{"id":243,"name":"성장드라마","categoryType":"keyword","priority":2},{"id":41,"name":"감성","categoryType":"keyword","priority":2},{"id":1,"name":"스토리","categoryType":"story","priority":1}]},"webtoonWeeks":[{"id":19581,"weekDay":"tue"}],"latestWebtoonEpisode":{"id":46331,"episode":44,"title":"39화","thumbnailImage":{"id":46331,"url":"http://t1.daumcdn.net/cartoon/5A12217F0242EE0002","width":0,"height":0,"serviceStatus":"service"},"episodeImage":{"id":0,"url":"http://t1.daumcdn.net/cartoon/5A1221810618F00001","width":0,"height":0,"serviceStatus":"service"},"encryptUseYn":"N","serviceStatus":"service","articleId":0,"dateCreated":"20171212000100","price":0,"isTopRecommend":false,"isPaid":false,"ticketAvailable":false},"webtoonServices":[{"id":33306,"webtoonId":1349,"serviceTarget":"series"},{"id":33307,"webtoonId":1349,"serviceTarget":"padtoon"},{"id":33308,"webtoonId":1349,"serviceTarget":"mobile"},{"id":33309,"webtoonId":1349,"serviceTarget":"app"}],"score":0.0,"isNew":false,"averageScore":9.900470219435737,"ranking":0,"diff":0,"metricsScore":0,"sort":"desc","sortWeight":0},{"id":1342,"nickname":"KingAndEmperor","webtoonType":"series","title":"왕 그리고 황제","finishYn":"N","titleImage2":{"id":0,"url":"http://t1.daumcdn.net/cartoon/589BF5900534860001","width":0,"height":0,"serviceStatus":"service"},"thumbnailImage":{"id":0,"url":"http://t1.daumcdn.net/cartoon/58898FD00207740001","width":0,"height":0,"serviceStatus":"service"},"thumbnailImage2":{"id":0,"url":"http://t1.daumcdn.net/cartoon/58898FC6024EF30001","width":0,"height":0,"serviceStatus":"service"},"padThumbnailImage":{"id":0,"url":"http://t1.daumcdn.net/cartoon/58898FE40265CA0001","width":0,"height":0,"serviceStatus":"service"},"homeThumbnailImage":{"id":0,"url":"http://t1.daumcdn.net/cartoon/58898FDA0203BB0001","width":0,"height":0,"serviceStatus":"service"},"appThumbnailImage":{"id":0,"url":"http://t1.daumcdn.net/cartoon/58898FED061F1A0002","width":0,"height":0,"serviceStatus":"service"},"pcThumbnailImage":{"id":0,"url":"http://t1.daumcdn.net/cartoon/589BF58A021C020001","width":0,"height":0,"serviceStatus":"service"},"pcRecommendImage":{"id":0,"url":"http://t1.daumcdn.net/webtoon/op/bc2830aba194bb04e66334ebc56ca88f1f93eb55","width":0,"height":0,"serviceStatus":"service"},"pcHomeImage":{"id":0,"url":"http://t1.daumcdn.net/cartoon/5889900E035D720001","width":0,"height":0,"serviceStatus":"service"},"pcHomeRightImage":{"id":0,"url":"http://t1.daumcdn.net/cartoon/588990190229B80001","width":0,"height":0,"serviceStatus":"service"},"pcHomeLeftColor":"434343","pcHomeRightColor":"434343","introduction":"영혼이 바뀐 고종과 태종, 그들은 조선을 바꿀 수 있을까?","startDate":"20170131000000","serviceStatus":"service","viewerType":"scroll","weekTerm":"weekly","articleId":0,"media":"daum","payYn":"N","payType":"free","price":0,"ageGrade":0,"restYn":"N","monopolize":"N","dateCreated":"20170126145944","webtoonComment":{"id":0,"articleId":1342,"commentUseYn":"N"},"cartoon":{"id":60667,"genres":[{"id":2,"name":"드라마"}],"artists":[{"id":10069,"name":"정이리이리","penName":"정이리이리","introduction":"2011년부터 만화를 그리고 있습니다 ","history":"2011 만화속세상 \u0027잡초이야기\u0027","smallPictureImage":{"id":29577650,"url":"http://i1.cartoon.daumcdn.net/svc/image/U03/cartoon/U748D0544D72CFED0F","width":0,"height":0,"serviceStatus":"service"},"appImage":{"id":44499555,"url":"http://i1.cartoon.daumcdn.net/svc/image/U03/cartoon/519476AE0311E60002","width":0,"height":0,"serviceStatus":"service"},"nameImage":{"id":29577651,"url":"http://i1.cartoon.daumcdn.net/svc/image/U03/cartoon/U9558254887CB93B01","width":0,"height":0,"serviceStatus":"service"},"birthDay":"19820202000000","debutDay":"20110306000000","email":"kenshin0202@daum.net","homepage":"https://www.instagram.com/jung121212/","blog":"http://blog.daum.net/kenshin0202","facebook":"","twitter":"","teamYn":"N","artistOrder":1,"artistType":"picture"},{"id":10069,"name":"정이리이리","penName":"정이리이리","introduction":"2011년부터 만화를 그리고 있습니다 ","history":"2011 만화속세상 \u0027잡초이야기\u0027","smallPictureImage":{"id":29577650,"url":"http://i1.cartoon.daumcdn.net/svc/image/U03/cartoon/U748D0544D72CFED0F","width":0,"height":0,"serviceStatus":"service"},"appImage":{"id":44499555,"url":"http://i1.cartoon.daumcdn.net/svc/image/U03/cartoon/519476AE0311E60002","width":0,"height":0,"serviceStatus":"service"},"nameImage":{"id":29577651,"url":"http://i1.cartoon.daumcdn.net/svc/image/U03/cartoon/U9558254887CB93B01","width":0,"height":0,"serviceStatus":"service"},"birthDay":"19820202000000","debutDay":"20110306000000","email":"kenshin0202@daum.net","homepage":"https://www.instagram.com/jung121212/","blog":"http://blog.daum.net/kenshin0202","facebook":"","twitter":"","teamYn":"N","artistOrder":1,"artistType":"story"}],"categories":[{"id":308,"name":"역사","categoryType":"keyword","priority":1},{"id":518,"name":"왕","categoryType":"keyword","priority":2},{"id":316,"name":"영혼","categoryType":"keyword","priority":2},{"id":395,"name":"조선시대","categoryType":"keyword","priority":2},{"id":1,"name":"스토리","categoryType":"story","priority":1}]},"webtoonWeeks":[{"id":20032,"weekDay":"tue"}],"latestWebtoonEpisode":{"id":46498,"episode":44,"title":"40화_진군(進軍)","thumbnailImage":{"id":46498,"url":"http://t1.daumcdn.net/cartoon/5A1C5544063B880001","width":0,"height":0,"serviceStatus":"service"},"episodeImage":{"id":0,"url":"http://t1.daumcdn.net/cartoon/5A1C5548025A270001","width":0,"height":0,"serviceStatus":"service"},"encryptUseYn":"N","serviceStatus":"service","articleId":0,"dateCreated":"20171212000100","price":0,"isTopRecommend":false,"isPaid":false,"ticketAvailable":false},"webtoonServices":[{"id":34912,"webtoonId":1342,"serviceTarget":"series"},{"id":34913,"webtoonId":1342,"serviceTarget":"padtoon"},{"id":34914,"webtoonId":1342,"serviceTarget":"mobile"},{"id":34915,"webtoonId":1342,"serviceTarget":"app"}],"score":0.0,"isNew":false,"averageScore":9.894199197373222,"ranking":0,"diff":0,"metricsScore":0,"sort":"desc","sortWeight":0},{"id":1339,"nickname":"jinx","webtoonType":"series","title":"징크스의 연인","finishYn":"N","titleImage2":{"id":0,"url":"http://t1.daumcdn.net/cartoon/586A13BD011EFA0001","width":0,"height":0,"serviceStatus":"service"},"thumbnailImage":{"id":0,"url":"http://t1.daumcdn.net/cartoon/58636B470538350001","width":0,"height":0,"serviceStatus":"service"},"thumbnailImage2":{"id":0,"url":"http://t1.daumcdn.net/cartoon/58636B410355EE0001","width":0,"height":0,"serviceStatus":"service"},"padThumbnailImage":{"id":0,"url":"http://t1.daumcdn.net/cartoon/5860D8FE0245F00001","width":0,"height":0,"serviceStatus":"service"},"homeThumbnailImage":{"id":0,"url":"http://t1.daumcdn.net/cartoon/58636B4C044C840001","width":0,"height":0,"serviceStatus":"service"},"appThumbnailImage":{"id":0,"url":"http://t1.daumcdn.net/cartoon/5860D905044CB60001","width":0,"height":0,"serviceStatus":"service"},"pcThumbnailImage":{"id":0,"url":"http://t1.daumcdn.net/cartoon/58636AB5021F030001","width":0,"height":0,"serviceStatus":"service"},"pcRecommendImage":{"id":0,"url":"http://t1.daumcdn.net/webtoon/op/abc87069aa616153f8166c32ede544e292bacdf3","width":0,"height":0,"serviceStatus":"service"},"pcHomeImage":{"id":0,"url":"http://t1.daumcdn.net/cartoon/58637AAD061A5C0002","width":0,"height":0,"serviceStatus":"service"},"pcHomeRightImage":{"id":0,"url":"http://t1.daumcdn.net/cartoon/58637AB505415F0002","width":0,"height":0,"serviceStatus":"service"},"pcHomeLeftColor":"e5a49b","pcHomeRightColor":"e5a49b","introduction":"재벌가가 숨겨둔 행운의 여신이 가난하고 재수 옴 붙은 내게로 왔다.","startDate":"20161227000000","serviceStatus":"service","viewerType":"scroll","weekTerm":"weekly","articleId":0,"media":"daum","payYn":"N","payType":"free","price":0,"ageGrade":0,"restYn":"N","monopolize":"N","dateCreated":"20161226174725","webtoonComment":{"id":0,"articleId":1339,"commentUseYn":"N"},"cartoon":{"id":60410,"genres":[{"id":2,"name":"드라마"}],"artists":[{"id":23177,"name":"구슬","penName":"구슬","introduction":"","nameImage":{"id":52848230,"url":"http://i1.cartoon.daumcdn.net/svc/image/U03/cartoon/5513DB290569B20002","width":0,"height":0,"serviceStatus":"service"},"debutDay":"20150326000000","email":"ycks0510@gmail.com","homepage":"https://twitter.com/beadS2seul","blog":"","facebook":"","twitter":"","teamYn":"N","artistOrder":1,"artistType":"picture"},{"id":18376,"name":"한지혜","penName":"한지혜","introduction":"","appImage":{"id":45841849,"url":"http://i1.cartoon.daumcdn.net/svc/image/U03/cartoon/51EB2AC50575590001","width":0,"height":0,"serviceStatus":"service"},"nameImage":{"id":46879291,"url":"http://i1.cartoon.daumcdn.net/svc/image/U03/cartoon/525606E6045AFD0005","width":0,"height":0,"serviceStatus":"service"},"birthDay":"20130721000000","debutDay":"20130721000000","email":"ddongfalnaby@naver.com","homepage":"","blog":"","facebook":"","twitter":"","teamYn":"N","artistOrder":1,"artistType":"story"}],"categories":[{"id":379,"name":"재벌","categoryType":"keyword","priority":1},{"id":483,"name":"희망","categoryType":"keyword","priority":2},{"id":34,"name":"가난","categoryType":"keyword","priority":2},{"id":127,"name":"돈","categoryType":"keyword","priority":2},{"id":1,"name":"스토리","categoryType":"story","priority":1}]},"webtoonWeeks":[{"id":19988,"weekDay":"tue"}],"latestWebtoonEpisode":{"id":46327,"episode":44,"title":"시즌2 18화","thumbnailImage":{"id":46327,"url":"http://t1.daumcdn.net/cartoon/5A12705303138A0001","width":0,"height":0,"serviceStatus":"service"},"episodeImage":{"id":0,"url":"http://t1.daumcdn.net/cartoon/5A12705A0666590001","width":0,"height":0,"serviceStatus":"service"},"encryptUseYn":"N","serviceStatus":"service","articleId":0,"dateCreated":"20171212000100","price":0,"isTopRecommend":false,"isPaid":false,"ticketAvailable":false},"webtoonServices":[{"id":34752,"webtoonId":1339,"serviceTarget":"series"},{"id":34753,"webtoonId":1339,"serviceTarget":"padtoon"},{"id":34754,"webtoonId":1339,"serviceTarget":"mobile"},{"id":34755,"webtoonId":1339,"serviceTarget":"app"}],"score":0.0,"isNew":false,"averageScore":9.930407191961924,"ranking":0,"diff":0,"metricsScore":0,"sort":"desc","sortWeight":0},{"id":1338,"nickname":"ItaewonClass","webtoonType":"series","title":"이태원 클라쓰","finishYn":"N","titleImage2":{"id":0,"url":"http://t1.daumcdn.net/cartoon/586A13A9050E150001","width":0,"height":0,"serviceStatus":"service"},"thumbnailImage":{"id":0,"url":"http://t1.daumcdn.net/cartoon/5860C9EA035D360003","width":0,"height":0,"serviceStatus":"service"},"thumbnailImage2":{"id":0,"url":"http://t1.daumcdn.net/cartoon/59226D8606616F0002","width":0,"height":0,"serviceStatus":"service"},"padThumbnailImage":{"id":0,"url":"http://t1.daumcdn.net/cartoon/5860C9F60247600001","width":0,"height":0,"serviceStatus":"service"},"homeThumbnailImage":{"id":0,"url":"http://t1.daumcdn.net/cartoon/5860C9F002561B0001","width":0,"height":0,"serviceStatus":"service"},"appThumbnailImage":{"id":0,"url":"http://t1.daumcdn.net/cartoon/59229D370203BE0001","width":0,"height":0,"serviceStatus":"service"},"pcThumbnailImage":{"id":0,"url":"http://t1.daumcdn.net/cartoon/5860CA03047D2B0002","width":0,"height":0,"serviceStatus":"service"},"pcRecommendImage":{"id":0,"url":"http://t1.daumcdn.net/webtoon/op/86ee171d14c027357fb4792bd1871e5132da14d9","width":0,"height":0,"serviceStatus":"service"},"pcHomeImage":{"id":0,"url":"http://t1.daumcdn.net/cartoon/5860CA85021B7F0001","width":0,"height":0,"serviceStatus":"service"},"pcHomeRightImage":{"id":0,"url":"http://t1.daumcdn.net/cartoon/5860CA8B023CDC0001","width":0,"height":0,"serviceStatus":"service"},"pcHomeLeftColor":"504641","pcHomeRightColor":"504641","introduction":"각자의 가치관이 어우러지는 이 곳, \u0027이태원\u0027. 이 거리를 살아가는 그들의 이야기","startDate":"20161227000000","serviceStatus":"service","viewerType":"scroll","weekTerm":"weekly","articleId":0,"media":"daum","payYn":"N","payType":"free","price":0,"ageGrade":0,"restYn":"N","monopolize":"N","dateCreated":"20161226164309","webtoonComment":{"id":0,"articleId":1338,"commentUseYn":"N"},"cartoon":{"id":60394,"genres":[{"id":2,"name":"드라마"}],"artists":[{"id":25687,"name":"광진","penName":"광진","pictureImage":{"id":54440243,"url":"http://t1.daumcdn.net/cartoon/2d133c1b7116f3d3b4401d0bbe42a7e43f7cf65c","width":0,"height":0,"serviceStatus":"service"},"daumEmailDisplayYn":"Y","homepage":"http://blog.naver.com/southwind7","artistOrder":0,"artistType":"picture"},{"id":25687,"name":"광진","penName":"광진","pictureImage":{"id":54440243,"url":"http://t1.daumcdn.net/cartoon/2d133c1b7116f3d3b4401d0bbe42a7e43f7cf65c","width":0,"height":0,"serviceStatus":"service"},"daumEmailDisplayYn":"Y","homepage":"http://blog.naver.com/southwind7","artistOrder":0,"artistType":"story"}],"categories":[{"id":426,"name":"청춘","categoryType":"keyword","priority":1},{"id":261,"name":"술","categoryType":"keyword","priority":2},{"id":243,"name":"성장드라마","categoryType":"keyword","priority":2},{"id":310,"name":"연애","categoryType":"keyword","priority":2},{"id":1,"name":"스토리","categoryType":"story","priority":1}]},"webtoonWeeks":[{"id":19989,"weekDay":"tue"}],"latestWebtoonEpisode":{"id":45961,"episode":53,"title":"3부 3화 바보","thumbnailImage":{"id":45961,"url":"http://t1.daumcdn.net/cartoon/5A00229A0227330001","width":0,"height":0,"serviceStatus":"service"},"episodeImage":{"id":0,"url":"http://t1.daumcdn.net/cartoon/5A00229C0229FE0001","width":0,"height":0,"serviceStatus":"service"},"encryptUseYn":"N","serviceStatus":"service","articleId":0,"dateCreated":"20171212000100","price":0,"isTopRecommend":false,"isPaid":false,"ticketAvailable":false},"webtoonServices":[{"id":34756,"webtoonId":1338,"serviceTarget":"series"},{"id":34757,"webtoonId":1338,"serviceTarget":"padtoon"},{"id":34758,"webtoonId":1338,"serviceTarget":"mobile"},{"id":34759,"webtoonId":1338,"serviceTarget":"app"}],"score":0.0,"isNew":false,"averageScore":9.947378383494227,"ranking":0,"diff":0,"metricsScore":0,"sort":"desc","sortWeight":0},{"id":1334,"nickname":"ishopping","webtoonType":"series","title":"아이쇼핑","finishYn":"N","titleImage2":{"id":0,"url":"http://t1.daumcdn.net/cartoon/584797D20202BF0002","width":0,"height":0,"serviceStatus":"service"},"thumbnailImage":{"id":0,"url":"http://t1.daumcdn.net/cartoon/584797B4023E080001","width":0,"height":0,"serviceStatus":"service"},"thumbnailImage2":{"id":0,"url":"http://t1.daumcdn.net/cartoon/584797AE065AE40001","width":0,"height":0,"serviceStatus":"service"},"padThumbnailImage":{"id":0,"url":"http://t1.daumcdn.net/cartoon/584797C0025E8A0002","width":0,"height":0,"serviceStatus":"service"},"homeThumbnailImage":{"id":0,"url":"http://t1.daumcdn.net/cartoon/584797BA023C5F0001","width":0,"height":0,"serviceStatus":"service"},"appThumbnailImage":{"id":0,"url":"http://t1.daumcdn.net/cartoon/584797C60518BB0001","width":0,"height":0,"serviceStatus":"service"},"pcThumbnailImage":{"id":0,"url":"http://t1.daumcdn.net/cartoon/58456077027B4A0001","width":0,"height":0,"serviceStatus":"service"},"pcRecommendImage":{"id":0,"url":"http://t1.daumcdn.net/webtoon/op/aacc601f0e3f1a5c7cb63a47f0213c1d003b5c20","width":0,"height":0,"serviceStatus":"service"},"pcHomeImage":{"id":0,"url":"http://t1.daumcdn.net/cartoon/58450F4E063EAA0001","width":0,"height":0,"serviceStatus":"service"},"pcHomeRightImage":{"id":0,"url":"http://t1.daumcdn.net/cartoon/584514F1050A570003","width":0,"height":0,"serviceStatus":"service"},"pcHomeLeftColor":"b25e50","pcHomeRightColor":"b25e50","introduction":"부모에게 살해당한 아이들, 그들의 복수가 시작된다.","startDate":"20161206000000","serviceStatus":"service","viewerType":"scroll","weekTerm":"weekly","articleId":0,"media":"daum","payYn":"N","payType":"free","price":0,"ageGrade":19,"restYn":"N","monopolize":"N","dateCreated":"20161205112144","webtoonComment":{"id":0,"articleId":1334,"commentUseYn":"N"},"cartoon":{"id":60255,"genres":[{"id":2,"name":"드라마"},{"id":14,"name":"스릴러"}],"artists":[{"id":26332,"name":"류가명","penName":"류가명","nameImage":{"id":54927497,"url":"http://t1.daumcdn.net/cartoon/5844C5410220A60001","width":0,"height":0,"serviceStatus":"service"},"debutDay":"20161206000000","teamYn":"N","artistOrder":1,"artistType":"picture"},{"id":12203,"name":"엄세윤","penName":"엄세윤","career":"다음 제 3회 온라인 공모전 장려상","smallPictureImage":{"id":33896667,"url":"http://t1.daumcdn.net/webtoon/op/9668b69363c0549ca977979f3b25f839e843acb1","width":0,"height":0,"serviceStatus":"service"},"appImage":{"id":44856178,"url":"http://i1.cartoon.daumcdn.net/svc/image/U03/cartoon/519474A40313A20004","width":0,"height":0,"serviceStatus":"service"},"nameImage":{"id":34372322,"url":"http://i1.cartoon.daumcdn.net/svc/image/U03/cartoon/4E809EDE0520FD00F8","width":0,"height":0,"serviceStatus":"service"},"birthDay":"19910101000000","debutDay":"20110826000000","blog":"http://blog.daum.net/91djatpdbs?t__nil_loginbox\u003dblog_btn","twitter":"https://twitter.com/91djatpdbs","teamYn":"N","artistOrder":1,"artistType":"story"}],"categories":[{"id":195,"name":"복수","categoryType":"keyword","priority":1},{"id":219,"name":"사회문제","categoryType":"keyword","priority":2},{"id":292,"name":"아이들","categoryType":"keyword","priority":2},{"id":226,"name":"살인","categoryType":"keyword","priority":2},{"id":1,"name":"스토리","categoryType":"story","priority":1}]},"webtoonWeeks":[{"id":19175,"weekDay":"tue"}],"latestWebtoonEpisode":{"id":45964,"episode":54,"title":"53화","thumbnailImage":{"id":45964,"url":"http://t1.daumcdn.net/cartoon/59FFE3BE021F030001","width":0,"height":0,"serviceStatus":"service"},"episodeImage":{"id":0,"url":"http://t1.daumcdn.net/cartoon/59FFE3C30256340001","width":0,"height":0,"serviceStatus":"service"},"encryptUseYn":"N","serviceStatus":"service","articleId":0,"dateCreated":"20171212000100","price":0,"isTopRecommend":false,"isPaid":false,"ticketAvailable":false},"webtoonServices":[{"id":31829,"webtoonId":1334,"serviceTarget":"series"},{"id":31830,"webtoonId":1334,"serviceTarget":"padtoon"},{"id":31831,"webtoonId":1334,"serviceTarget":"mobile"},{"id":31832,"webtoonId":1334,"serviceTarget":"app"}],"score":0.0,"isNew":false,"averageScore":9.855813360530341,"ranking":0,"diff":0,"metricsScore":0,"sort":"desc","sortWeight":0},{"id":1332,"nickname":"Pygmalion","webtoonType":"series","title":"피그말리온 컴플렉스","finishYn":"N","titleImage2":{"id":0,"url":"http://t1.daumcdn.net/cartoon/583BFEFE053FAE0001","width":0,"height":0,"serviceStatus":"service"},"thumbnailImage":{"id":0,"url":"http://t1.daumcdn.net/cartoon/583285E802421F0001","width":0,"height":0,"serviceStatus":"service"},"thumbnailImage2":{"id":0,"url":"http://t1.daumcdn.net/webtoon/op/a42263b2fcae6d2557ecaf7c69fe0a89a38625e4","width":0,"height":0,"serviceStatus":"service"},"padThumbnailImage":{"id":0,"url":"http://t1.daumcdn.net/cartoon/583285F704572B0001","width":0,"height":0,"serviceStatus":"service"},"homeThumbnailImage":{"id":0,"url":"http://t1.daumcdn.net/cartoon/583285EF054F9F0001","width":0,"height":0,"serviceStatus":"service"},"appThumbnailImage":{"id":0,"url":"http://t1.daumcdn.net/webtoon/op/072c43b22f8042aef26cf384785c435a48470338","width":0,"height":0,"serviceStatus":"service"},"pcThumbnailImage":{"id":0,"url":"http://t1.daumcdn.net/webtoon/op/d1df6af63473c99eaa00284b1dc9f5ca2ca9783b","width":0,"height":0,"serviceStatus":"service"},"pcRecommendImage":{"id":0,"url":"http://t1.daumcdn.net/webtoon/op/78941818efd22524e30cc3b720bd7148d67f61f6","width":0,"height":0,"serviceStatus":"service"},"pcHomeImage":{"id":0,"url":"http://t1.daumcdn.net/webtoon/op/8074cec1a3199463db197c7244c86df49088710d","width":0,"height":0,"serviceStatus":"service"},"pcHomeRightImage":{"id":0,"url":"http://t1.daumcdn.net/webtoon/op/95cbe68fc0f4ba8ad4e768754ff6dfcec961447c","width":0,"height":0,"serviceStatus":"service"},"pcHomeLeftColor":"a0bbcd","pcHomeRightColor":"a0bbcd","introduction":"금수저 학교에 잠입한 고아 소매치기 소녀의 삼단변신(?)이 시작된다!","startDate":"20161122000000","serviceStatus":"service","viewerType":"scroll","weekTerm":"weekly","articleId":0,"media":"daum","payYn":"N","payType":"free","price":0,"ageGrade":0,"restYn":"N","monopolize":"N","dateCreated":"20161121142911","webtoonComment":{"id":0,"articleId":1332,"commentUseYn":"N"},"cartoon":{"id":60173,"genres":[{"id":1,"name":"학원"},{"id":5,"name":"순정"}],"artists":[{"id":23215,"name":"문미영","penName":"문미영","introduction":"2014 만화공모대전2 본선 진출","nameImage":{"id":52895443,"url":"http://i1.cartoon.daumcdn.net/svc/image/U03/cartoon/551B4FDA0457690026","width":0,"height":0,"serviceStatus":"service"},"debutDay":"20150401000000","email":"moonie131@hanmail.net","homepage":"","blog":"","facebook":"http://www.facebook.com/moonie131","twitter":"","teamYn":"N","artistOrder":1,"artistType":"picture"},{"id":23215,"name":"문미영","penName":"문미영","introduction":"2014 만화공모대전2 본선 진출","nameImage":{"id":52895443,"url":"http://i1.cartoon.daumcdn.net/svc/image/U03/cartoon/551B4FDA0457690026","width":0,"height":0,"serviceStatus":"service"},"debutDay":"20150401000000","email":"moonie131@hanmail.net","homepage":"","blog":"","facebook":"http://www.facebook.com/moonie131","twitter":"","teamYn":"N","artistOrder":1,"artistType":"story"}],"categories":[{"id":464,"name":"학교생활","categoryType":"keyword","priority":1},{"id":243,"name":"성장드라마","categoryType":"keyword","priority":2},{"id":34,"name":"가난","categoryType":"keyword","priority":2},{"id":310,"name":"연애","categoryType":"keyword","priority":2},{"id":1,"name":"스토리","categoryType":"story","priority":0}]},"webtoonWeeks":[{"id":19925,"weekDay":"tue"}],"latestWebtoonEpisode":{"id":46482,"episode":51,"title":"43화","thumbnailImage":{"id":46482,"url":"http://t1.daumcdn.net/cartoon/5A1BC0AC027BD20001","width":0,"height":0,"serviceStatus":"service"},"episodeImage":{"id":0,"url":"http://t1.daumcdn.net/cartoon/5A1BC0AF02022A0001","width":0,"height":0,"serviceStatus":"service"},"encryptUseYn":"N","serviceStatus":"service","articleId":0,"dateCreated":"20171212000100","price":0,"isTopRecommend":false,"isPaid":false,"ticketAvailable":false},"webtoonServices":[{"id":34504,"webtoonId":1332,"serviceTarget":"series"},{"id":34505,"webtoonId":1332,"serviceTarget":"padtoon"},{"id":34506,"webtoonId":1332,"serviceTarget":"mobile"},{"id":34507,"webtoonId":1332,"serviceTarget":"app"}],"score":0.0,"isNew":false,"averageScore":9.824719595337585,"ranking":0,"diff":0,"metricsScore":0,"sort":"desc","sortWeight":0},{"id":1305,"nickname":"murdercase","webtoonType":"series","title":"월령관 살인사건 ","finishYn":"N","titleImage2":{"id":0,"url":"http://t1.daumcdn.net/cartoon/5860DB510243EB0001","width":0,"height":0,"serviceStatus":"service"},"thumbnailImage":{"id":0,"url":"http://i1.cartoon.daumcdn.net/svc/image/U03/cartoon/57678EA10523F90001","width":0,"height":0,"serviceStatus":"service"},"thumbnailImage2":{"id":0,"url":"http://i1.cartoon.daumcdn.net/svc/image/U03/cartoon/57678E9A061D570001","width":0,"height":0,"serviceStatus":"service"},"padThumbnailImage":{"id":0,"url":"http://i1.cartoon.daumcdn.net/svc/image/U03/cartoon/57678EAF055D900001","width":0,"height":0,"serviceStatus":"service"},"homeThumbnailImage":{"id":0,"url":"http://i1.cartoon.daumcdn.net/svc/image/U03/cartoon/57678EA8031D6F0001","width":0,"height":0,"serviceStatus":"service"},"appThumbnailImage":{"id":0,"url":"http://i1.cartoon.daumcdn.net/svc/image/U03/cartoon/576792E20115AA0001","width":0,"height":0,"serviceStatus":"service"},"pcThumbnailImage":{"id":0,"url":"http://i1.cartoon.daumcdn.net/svc/image/U03/cartoon/57690AB80353570001","width":0,"height":0,"serviceStatus":"service"},"pcRecommendImage":{"id":0,"url":"http://t1.daumcdn.net/webtoon/op/595d6a3315d7b0c1fd666640e1116ee2f97010d0","width":0,"height":0,"serviceStatus":"service"},"pcHomeImage":{"id":0,"url":"http://i1.cartoon.daumcdn.net/svc/image/U03/cartoon/57678CFA02164C0001","width":0,"height":0,"serviceStatus":"service"},"pcHomeRightImage":{"id":0,"url":"http://i1.cartoon.daumcdn.net/svc/image/U03/cartoon/57678D02057DBE0001","width":0,"height":0,"serviceStatus":"service"},"pcHomeLeftColor":"262626","pcHomeRightColor":"2f2f2f","introduction":"100여 년 전, 의문의 살인사건이 벌어졌던 낡은 서양식 저택에서 또 다시 사건이 일어난다!","startDate":"20160621000000","serviceStatus":"service","viewerType":"scroll","weekTerm":"weekly","articleId":0,"media":"daum","payYn":"N","payType":"free","price":0,"ageGrade":0,"restYn":"N","monopolize":"N","dateCreated":"20160620152831","webtoonComment":{"id":0,"articleId":1305,"commentUseYn":"N"},"cartoon":{"id":59136,"genres":[{"id":2,"name":"드라마"},{"id":14,"name":"스릴러"}],"artists":[{"id":22698,"name":"곡","penName":"곡","nameImage":{"id":52234731,"url":"http://i1.cartoon.daumcdn.net/svc/image/U03/cartoon/54CA02EB050B8E0001","width":0,"height":0,"serviceStatus":"service"},"teamYn":"N","artistOrder":1,"artistType":"picture"},{"id":13286,"name":"마하로","penName":"마하로","appImage":{"id":44855712,"url":"http://i1.cartoon.daumcdn.net/svc/image/U03/cartoon/519471200552370003","width":0,"height":0,"serviceStatus":"service"},"nameImage":{"id":35165760,"url":"http://i1.cartoon.daumcdn.net/svc/image/U03/cartoon/4E8672AD02349F0001","width":0,"height":0,"serviceStatus":"service"},"debutDay":"20111001000000","email":"lamatinee@daum.net","blog":"http://blog.naver.com/maharo7","teamYn":"N","artistOrder":1,"artistType":"story"}],"categories":[{"id":227,"name":"살인사건","categoryType":"keyword","priority":1},{"id":430,"name":"추리","categoryType":"keyword","priority":2},{"id":317,"name":"영화","categoryType":"keyword","priority":2},{"id":195,"name":"복수","categoryType":"keyword","priority":2},{"id":1,"name":"스토리","categoryType":"story","priority":1}]},"webtoonWeeks":[{"id":19967,"weekDay":"tue"}],"latestWebtoonEpisode":{"id":46337,"episode":71,"title":"66화","thumbnailImage":{"id":46337,"url":"http://t1.daumcdn.net/cartoon/5A12ABD90220E30001","width":0,"height":0,"serviceStatus":"service"},"episodeImage":{"id":0,"url":"http://t1.daumcdn.net/cartoon/5A12AB790579E50001","width":0,"height":0,"serviceStatus":"service"},"encryptUseYn":"N","serviceStatus":"service","articleId":0,"dateCreated":"20171212000100","price":0,"isTopRecommend":false,"isPaid":false,"ticketAvailable":false},"webtoonServices":[{"id":34660,"webtoonId":1305,"serviceTarget":"series"},{"id":34661,"webtoonId":1305,"serviceTarget":"padtoon"},{"id":34662,"webtoonId":1305,"serviceTarget":"mobile"},{"id":34663,"webtoonId":1305,"serviceTarget":"app"}],"score":0.0,"isNew":false,"averageScore":9.859571180220204,"ranking":0,"diff":0,"metricsScore":0,"sort":"desc","sortWeight":0},{"id":1304,"nickname":"girlsinsun","webtoonType":"series","title":"소녀신선","finishYn":"N","titleImage2":{"id":0,"url":"http://t1.daumcdn.net/cartoon/58980F640258440001","width":0,"height":0,"serviceStatus":"service"},"thumbnailImage":{"id":0,"url":"http://i1.cartoon.daumcdn.net/svc/image/U03/cartoon/576789EA015E120001","width":0,"height":0,"serviceStatus":"service"},"thumbnailImage2":{"id":0,"url":"http://i1.cartoon.daumcdn.net/svc/image/U03/cartoon/576789E30474DE0001","width":0,"height":0,"serviceStatus":"service"},"padThumbnailImage":{"id":0,"url":"http://i1.cartoon.daumcdn.net/svc/image/U03/cartoon/57678A060403B10004","width":0,"height":0,"serviceStatus":"service"},"homeThumbnailImage":{"id":0,"url":"http://i1.cartoon.daumcdn.net/svc/image/U03/cartoon/576789F10540030001","width":0,"height":0,"serviceStatus":"service"},"appThumbnailImage":{"id":0,"url":"http://i1.cartoon.daumcdn.net/svc/image/U03/cartoon/5768946F0240B20001","width":0,"height":0,"serviceStatus":"service"},"pcThumbnailImage":{"id":0,"url":"http://t1.daumcdn.net/webtoon/op/8966f696ba45f43e918e05d07ee10921bc7f29b5","width":0,"height":0,"serviceStatus":"service"},"pcRecommendImage":{"id":0,"url":"http://t1.daumcdn.net/webtoon/op/2475f904ed18dda40e5b816cbb59a40fcaf942e6","width":0,"height":0,"serviceStatus":"service"},"pcHomeImage":{"id":0,"url":"http://i1.cartoon.daumcdn.net/svc/image/U03/cartoon/5767937E02726F0001","width":0,"height":0,"serviceStatus":"service"},"pcHomeRightImage":{"id":0,"url":"http://i1.cartoon.daumcdn.net/svc/image/U03/cartoon/576793850231820001","width":0,"height":0,"serviceStatus":"service"},"pcHomeLeftColor":"716b53","pcHomeRightColor":"625b44","introduction":"재수생 하버들, 신선이 되어 성질 드러운 이무기 \u0027꽝철이\u0027와 만나다","startDate":"20160621000000","restartDate":"20170202000000","serviceStatus":"service","viewerType":"scroll","weekTerm":"weekly","articleId":0,"media":"daum","payYn":"N","payType":"free","price":0,"ageGrade":0,"restYn":"N","monopolize":"N","dateCreated":"20160620145056","webtoonComment":{"id":0,"articleId":1304,"commentUseYn":"N"},"cartoon":{"id":59135,"genres":[{"id":12,"name":"액션"},{"id":4,"name":"판타지"}],"artists":[{"id":13344,"name":"효미","penName":"효미","pictureImage":{"id":35213759,"url":"http://i1.cartoon.daumcdn.net/svc/image/U03/cartoon/57678A15060B8C0001","width":0,"height":0,"serviceStatus":"service"},"nameImage":{"id":54403761,"url":"http://i1.cartoon.daumcdn.net/svc/image/U03/cartoon/5767803004402D0001","width":0,"height":0,"serviceStatus":"service"},"birthDay":"19820101000000","debutDay":"20090101000000","teamYn":"N","artistOrder":1,"artistType":"picture"},{"id":13344,"name":"효미","penName":"효미","pictureImage":{"id":35213759,"url":"http://i1.cartoon.daumcdn.net/svc/image/U03/cartoon/57678A15060B8C0001","width":0,"height":0,"serviceStatus":"service"},"nameImage":{"id":54403761,"url":"http://i1.cartoon.daumcdn.net/svc/image/U03/cartoon/5767803004402D0001","width":0,"height":0,"serviceStatus":"service"},"birthDay":"19820101000000","debutDay":"20090101000000","teamYn":"N","artistOrder":1,"artistType":"story"}],"categories":[{"id":241,"name":"설화","categoryType":"keyword","priority":1},{"id":448,"name":"퇴마","categoryType":"keyword","priority":2},{"id":491,"name":"소녀","categoryType":"keyword","priority":2},{"id":1,"name":"스토리","categoryType":"story","priority":0}]},"webtoonWeeks":[{"id":19530,"weekDay":"tue"}],"latestWebtoonEpisode":{"id":46477,"episode":61,"title":"54화 삼목이 이야기4","thumbnailImage":{"id":46477,"url":"http://t1.daumcdn.net/cartoon/5A1BDD1F021C690001","width":0,"height":0,"serviceStatus":"service"},"episodeImage":{"id":0,"url":"http://t1.daumcdn.net/cartoon/5A1BDD230145900001","width":0,"height":0,"serviceStatus":"service"},"encryptUseYn":"N","serviceStatus":"service","articleId":0,"dateCreated":"20171212000100","price":0,"isTopRecommend":false,"isPaid":false,"ticketAvailable":false},"webtoonServices":[{"id":33112,"webtoonId":1304,"serviceTarget":"series"},{"id":33113,"webtoonId":1304,"serviceTarget":"padtoon"},{"id":33114,"webtoonId":1304,"serviceTarget":"mobile"},{"id":33115,"webtoonId":1304,"serviceTarget":"app"}],"score":0.0,"isNew":false,"averageScore":9.914063176114237,"ranking":0,"diff":0,"metricsScore":0,"sort":"desc","sortWeight":0},{"id":1286,"nickname":"seaweed","webtoonType":"series","title":"매생이가 나타났다","englishTitle":"Green Sea Weed","finishYn":"N","titleImage2":{"id":0,"url":"http://t1.daumcdn.net/cartoon/5832C5B50469160001","width":0,"height":0,"serviceStatus":"service"},"thumbnailImage":{"id":0,"url":"http://i1.cartoon.daumcdn.net/svc/image/U03/cartoon/5721D7570335D60001","width":0,"height":0,"serviceStatus":"service"},"thumbnailImage2":{"id":0,"url":"http://i1.cartoon.daumcdn.net/svc/image/U03/cartoon/5721D75302380C0002","width":0,"height":0,"serviceStatus":"service"},"padThumbnailImage":{"id":0,"url":"http://i1.cartoon.daumcdn.net/svc/image/U03/cartoon/5721D75E020A340001","width":0,"height":0,"serviceStatus":"service"},"homeThumbnailImage":{"id":0,"url":"http://i1.cartoon.daumcdn.net/svc/image/U03/cartoon/5721D75B011F450001","width":0,"height":0,"serviceStatus":"service"},"appThumbnailImage":{"id":0,"url":"http://i1.cartoon.daumcdn.net/svc/image/U03/cartoon/5721D764026B6C0001","width":0,"height":0,"serviceStatus":"service"},"pcThumbnailImage":{"id":0,"url":"http://i1.cartoon.daumcdn.net/svc/image/U03/cartoon/5721D7690204400005","width":0,"height":0,"serviceStatus":"service"},"pcRecommendImage":{"id":0,"url":"http://t1.daumcdn.net/webtoon/op/31210a02cb3d095ec341a1d850206485a0168d95","width":0,"height":0,"serviceStatus":"service"},"pcHomeImage":{"id":0,"url":"http://i1.cartoon.daumcdn.net/svc/image/U03/cartoon/572300DC0238240001","width":0,"height":0,"serviceStatus":"service"},"pcHomeRightImage":{"id":0,"url":"http://i1.cartoon.daumcdn.net/svc/image/U03/cartoon/572300E2054E670001","width":0,"height":0,"serviceStatus":"service"},"pcHomeLeftColor":"ee9696","pcHomeRightColor":"ec8b8a","introduction":"연애만 빼고 다 잘하는 여대생 도형에게 들이닥친 초록색 그것(?)과의 파란만장 하숙 생활. 만화공모대전3 우수상 수상작","startDate":"20160503000000","serviceStatus":"service","viewerType":"scroll","weekTerm":"weekly","articleId":0,"media":"daum","payYn":"N","payType":"free","price":0,"ageGrade":0,"restYn":"Y","monopolize":"N","dateCreated":"20160428182735","webtoonComment":{"id":0,"articleId":1286,"commentUseYn":"N"},"cartoon":{"id":58777,"genres":[{"id":6,"name":"코믹"},{"id":5,"name":"순정"}],"artists":[{"id":25449,"name":"오청","penName":"오청","career":"다음 온라인 만화공모대전3 우수상","pictureImage":{"id":54291264,"url":"http://i1.cartoon.daumcdn.net/svc/image/U03/cartoon/57304D4E0231570001","width":0,"height":0,"serviceStatus":"service"},"nameImage":{"id":54249882,"url":"http://i1.cartoon.daumcdn.net/svc/image/U03/cartoon/5721D516027B830001","width":0,"height":0,"serviceStatus":"service"},"debutDay":"20160503000000","email":"5_cjd@hanmail.net","homepage":"http://twitter.com/5_cjd","twitter":"http://twitter.com/5_cjd","teamYn":"N","artistOrder":1,"artistType":"picture"},{"id":25449,"name":"오청","penName":"오청","career":"다음 온라인 만화공모대전3 우수상","pictureImage":{"id":54291264,"url":"http://i1.cartoon.daumcdn.net/svc/image/U03/cartoon/57304D4E0231570001","width":0,"height":0,"serviceStatus":"service"},"nameImage":{"id":54249882,"url":"http://i1.cartoon.daumcdn.net/svc/image/U03/cartoon/5721D516027B830001","width":0,"height":0,"serviceStatus":"service"},"debutDay":"20160503000000","email":"5_cjd@hanmail.net","homepage":"http://twitter.com/5_cjd","twitter":"http://twitter.com/5_cjd","teamYn":"N","artistOrder":1,"artistType":"story"}],"categories":[{"id":93,"name":"꽃미남","categoryType":"keyword","priority":1},{"id":173,"name":"미남미녀","categoryType":"keyword","priority":2},{"id":324,"name":"왕자","categoryType":"keyword","priority":2},{"id":418,"name":"짝사랑","categoryType":"keyword","priority":2},{"id":2,"name":"에피소드","categoryType":"story","priority":0}]},"webtoonWeeks":[{"id":19994,"weekDay":"tue"}],"latestWebtoonEpisode":{"id":46478,"episode":67,"title":"61화","thumbnailImage":{"id":46478,"url":"http://t1.daumcdn.net/cartoon/5A1BDF56043CE70001","width":0,"height":0,"serviceStatus":"service"},"encryptUseYn":"N","serviceStatus":"service","articleId":0,"dateCreated":"20171128000000","price":0,"isTopRecommend":false,"isPaid":false,"ticketAvailable":false},"webtoonServices":[{"id":34772,"webtoonId":1286,"serviceTarget":"series"},{"id":34773,"webtoonId":1286,"serviceTarget":"padtoon"},{"id":34774,"webtoonId":1286,"serviceTarget":"mobile"},{"id":34775,"webtoonId":1286,"serviceTarget":"app"}],"score":0.0,"isNew":false,"averageScore":9.897466539196941,"ranking":0,"diff":0,"metricsScore":0,"sort":"desc","sortWeight":0},{"id":1270,"nickname":"fairytale","webtoonType":"series","title":"그림형제 잔혹동화","finishYn":"N","titleImage2":{"id":0,"url":"http://t1.daumcdn.net/cartoon/583D51E7036F970001","width":0,"height":0,"serviceStatus":"service"},"thumbnailImage":{"id":0,"url":"http://i1.cartoon.daumcdn.net/svc/image/U03/cartoon/56CA964E0222E90001","width":0,"height":0,"serviceStatus":"service"},"thumbnailImage2":{"id":0,"url":"http://i1.cartoon.daumcdn.net/svc/image/U03/cartoon/56CA9784026ACE0001","width":0,"height":0,"serviceStatus":"service"},"padThumbnailImage":{"id":0,"url":"http://i1.cartoon.daumcdn.net/svc/image/U03/cartoon/56CA96570253790001","width":0,"height":0,"serviceStatus":"service"},"homeThumbnailImage":{"id":0,"url":"http://i1.cartoon.daumcdn.net/svc/image/U03/cartoon/56CA96530441AD0001","width":0,"height":0,"serviceStatus":"service"},"appThumbnailImage":{"id":0,"url":"http://i1.cartoon.daumcdn.net/svc/image/U03/cartoon/56CA965C0350150003","width":0,"height":0,"serviceStatus":"service"},"pcThumbnailImage":{"id":0,"url":"http://i1.cartoon.daumcdn.net/svc/image/U03/cartoon/56CA96790175B30001","width":0,"height":0,"serviceStatus":"service"},"pcRecommendImage":{"id":0,"url":"http://t1.daumcdn.net/webtoon/op/6f4b31e98e4f6e7811415062fa684a75dc98ec40","width":0,"height":0,"serviceStatus":"service"},"pcHomeImage":{"id":0,"url":"http://i1.cartoon.daumcdn.net/svc/image/U03/cartoon/56CA96BC015D970001","width":0,"height":0,"serviceStatus":"service"},"pcHomeRightImage":{"id":0,"url":"http://i1.cartoon.daumcdn.net/svc/image/U03/cartoon/56CA96C302689B0002","width":0,"height":0,"serviceStatus":"service"},"pcHomeLeftColor":"231816","pcHomeRightColor":"261b19","introduction":"아름다운 그림형제의 동화 속 이야기들. 그 동화의 잔혹한 비밀이 공개된다!","startDate":"20160223000000","serviceStatus":"service","viewerType":"scroll","weekTerm":"weekly","articleId":0,"media":"daum","payYn":"N","payType":"free","price":0,"ageGrade":0,"restYn":"N","monopolize":"N","dateCreated":"20160222140424","webtoonComment":{"id":0,"articleId":1270,"commentUseYn":"N"},"cartoon":{"id":58209,"genres":[{"id":14,"name":"스릴러"},{"id":2,"name":"드라마"}],"artists":[{"id":25042,"name":"Crom","penName":"Crom","nameImage":{"id":54080479,"url":"http://i1.cartoon.daumcdn.net/svc/image/U03/cartoon/56C6DBDD027EE70002","width":0,"height":0,"serviceStatus":"service"},"debutDay":"20160223000000","email":"lion2307@hanmail.net","teamYn":"N","artistOrder":1,"artistType":"picture"},{"id":25042,"name":"Crom","penName":"Crom","nameImage":{"id":54080479,"url":"http://i1.cartoon.daumcdn.net/svc/image/U03/cartoon/56C6DBDD027EE70002","width":0,"height":0,"serviceStatus":"service"},"debutDay":"20160223000000","email":"lion2307@hanmail.net","teamYn":"N","artistOrder":1,"artistType":"story"}],"categories":[{"id":70,"name":"괴담","categoryType":"keyword","priority":1},{"id":59,"name":"고전","categoryType":"keyword","priority":2},{"id":83,"name":"그림기법","categoryType":"keyword","priority":2},{"id":135,"name":"동화","categoryType":"keyword","priority":2},{"id":3,"name":"옴니버스","categoryType":"story","priority":1}]},"webtoonWeeks":[{"id":18884,"weekDay":"tue"}],"latestWebtoonEpisode":{"id":46484,"episode":95,"title":"91화 수수께끼 (6)","thumbnailImage":{"id":46484,"url":"http://t1.daumcdn.net/cartoon/5A1BA4CB0264400001","width":0,"height":0,"serviceStatus":"service"},"episodeImage":{"id":0,"url":"http://t1.daumcdn.net/cartoon/5A1BA4CD0267150001","width":0,"height":0,"serviceStatus":"service"},"encryptUseYn":"N","serviceStatus":"service","articleId":0,"dateCreated":"20171212000100","price":0,"isTopRecommend":false,"isPaid":false,"ticketAvailable":false},"webtoonServices":[{"id":30904,"webtoonId":1270,"serviceTarget":"series"},{"id":30905,"webtoonId":1270,"serviceTarget":"padtoon"},{"id":30906,"webtoonId":1270,"serviceTarget":"mobile"},{"id":30907,"webtoonId":1270,"serviceTarget":"app"}],"score":0.0,"isNew":false,"averageScore":9.412446613788896,"ranking":0,"diff":0,"metricsScore":0,"sort":"desc","sortWeight":0},{"id":1190,"nickname":"iammother","webtoonType":"series","title":"나는 엄마다","finishYn":"N","titleImage2":{"id":0,"url":"http://t1.daumcdn.net/cartoon/58B7D4FB0606490001","width":0,"height":0,"serviceStatus":"service"},"thumbnailImage":{"id":0,"url":"http://t1.daumcdn.net/cartoon/58B7D344035BCC0001","width":0,"height":0,"serviceStatus":"service"},"thumbnailImage2":{"id":0,"url":"http://t1.daumcdn.net/cartoon/58B7D33D037CF30001","width":0,"height":0,"serviceStatus":"service"},"padThumbnailImage":{"id":0,"url":"http://t1.daumcdn.net/cartoon/58B7D3590234BA0001","width":0,"height":0,"serviceStatus":"service"},"homeThumbnailImage":{"id":0,"url":"http://t1.daumcdn.net/cartoon/58B7D34A025C950001","width":0,"height":0,"serviceStatus":"service"},"appThumbnailImage":{"id":0,"url":"http://t1.daumcdn.net/cartoon/58B7D41302084C0001","width":0,"height":0,"serviceStatus":"service"},"pcThumbnailImage":{"id":0,"url":"http://t1.daumcdn.net/webtoon/op/08c3160a6dabca73d58170fbafb99778f10ad4cc","width":0,"height":0,"serviceStatus":"service"},"pcRecommendImage":{"id":0,"url":"http://t1.daumcdn.net/webtoon/op/4073a057309c90fb4c721991db09c8a79ee4684a","width":0,"height":0,"serviceStatus":"service"},"pcHomeImage":{"id":0,"url":"http://t1.daumcdn.net/cartoon/58F41E840263B80002","width":0,"height":0,"serviceStatus":"service"},"pcHomeRightImage":{"id":0,"url":"http://t1.daumcdn.net/cartoon/58B7D386010F550001","width":0,"height":0,"serviceStatus":"service"},"pcHomeLeftColor":"d69334","pcHomeRightColor":"d69334","introduction":"현재 엄마인 사람들 혹은 아닌 사람들 모두 공감하는 엄마의 이야기","startDate":"20150317000000","serviceStatus":"service","viewerType":"scroll","weekTerm":"weekly","articleId":0,"media":"daum","payYn":"N","payType":"free","price":0,"ageGrade":0,"restYn":"N","monopolize":"N","dateCreated":"20150316201605","webtoonComment":{"id":0,"articleId":1190,"commentUseYn":"N"},"cartoon":{"id":55168,"genres":[{"id":10,"name":"일상"}],"artists":[{"id":17124,"name":"순두부","penName":"순두부","introduction":"안녕하세요.","pictureImage":{"id":52792962,"url":"http://i1.cartoon.daumcdn.net/svc/image/U03/cartoon/56257A22041E3E0001","width":0,"height":0,"serviceStatus":"service"},"email":"2336460@naver.com","homepage":"http://blog.naver.com/2336460","blog":"http://blog.naver.com/2336460","artistOrder":0,"artistType":"picture"},{"id":17124,"name":"순두부","penName":"순두부","introduction":"안녕하세요.","pictureImage":{"id":52792962,"url":"http://i1.cartoon.daumcdn.net/svc/image/U03/cartoon/56257A22041E3E0001","width":0,"height":0,"serviceStatus":"service"},"email":"2336460@naver.com","homepage":"http://blog.naver.com/2336460","blog":"http://blog.naver.com/2336460","artistOrder":0,"artistType":"story"}],"categories":[{"id":345,"name":"육아","categoryType":"keyword","priority":1},{"id":51,"name":"결혼생활","categoryType":"keyword","priority":2},{"id":292,"name":"아이들","categoryType":"keyword","priority":2},{"id":301,"name":"엄마","categoryType":"keyword","priority":2},{"id":2,"name":"에피소드","categoryType":"story","priority":0}]},"webtoonWeeks":[{"id":19782,"weekDay":"tue"}],"latestWebtoonEpisode":{"id":46487,"episode":124,"title":"113화 조급한 마음","thumbnailImage":{"id":46487,"url":"http://t1.daumcdn.net/cartoon/5A1B84FE0256CC0002","width":0,"height":0,"serviceStatus":"service"},"episodeImage":{"id":0,"url":"http://t1.daumcdn.net/cartoon/5A1B85010251910002","width":0,"height":0,"serviceStatus":"service"},"encryptUseYn":"N","serviceStatus":"service","articleId":0,"dateCreated":"20171212000100","price":0,"isTopRecommend":false,"isPaid":false,"ticketAvailable":false},"webtoonServices":[{"id":33977,"webtoonId":1190,"serviceTarget":"series"},{"id":33978,"webtoonId":1190,"serviceTarget":"padtoon"},{"id":33979,"webtoonId":1190,"serviceTarget":"mobile"},{"id":33980,"webtoonId":1190,"serviceTarget":"app"}],"score":0.0,"isNew":false,"averageScore":9.801088570014844,"ranking":0,"diff":0,"metricsScore":0,"sort":"desc","sortWeight":0},{"id":940,"nickname":"tomorrow","webtoonType":"series","title":"어제 오늘 그리고 내일","finishYn":"N","titleImage2":{"id":0,"url":"http://i1.cartoon.daumcdn.net/svc/image/U03/cartoon/57CCC0AE047F4B0001","width":0,"height":0,"serviceStatus":"service"},"thumbnailImage":{"id":0,"url":"http://i1.cartoon.daumcdn.net/svc/image/U03/cartoon/51626DD8054BEB0001","width":0,"height":0,"serviceStatus":"service"},"thumbnailImage2":{"id":0,"url":"http://i1.cartoon.daumcdn.net/svc/image/U03/cartoon/554942A00218250001","width":0,"height":0,"serviceStatus":"service"},"padThumbnailImage":{"id":0,"url":"http://i1.cartoon.daumcdn.net/svc/image/U03/cartoon/51626E680549460003","width":0,"height":0,"serviceStatus":"service"},"homeThumbnailImage":{"id":0,"url":"http://i1.cartoon.daumcdn.net/svc/image/U03/cartoon/51626E5601555D0001","width":0,"height":0,"serviceStatus":"service"},"appThumbnailImage":{"id":0,"url":"http://i1.cartoon.daumcdn.net/svc/image/U03/cartoon/517F483302151A000B","width":0,"height":0,"serviceStatus":"service"},"pcThumbnailImage":{"id":0,"url":"http://t1.daumcdn.net/webtoon/op/65470644d175c51f94c9ef90b99ccdf3cc77760a","width":0,"height":0,"serviceStatus":"service"},"pcRecommendImage":{"id":0,"url":"http://t1.daumcdn.net/webtoon/op/8721fee360067ae660a9b873c846439b3a027a18","width":0,"height":0,"serviceStatus":"service"},"pcHomeImage":{"id":0,"url":"http://i1.cartoon.daumcdn.net/svc/image/U03/cartoon/55F7C94A02655D0001","width":0,"height":0,"serviceStatus":"service"},"pcHomeRightImage":{"id":0,"url":"http://i1.cartoon.daumcdn.net/svc/image/U03/cartoon/55F7C951024A1C0003","width":0,"height":0,"serviceStatus":"service"},"pcHomeLeftColor":"904c6a","pcHomeRightColor":"b06382","introduction":"하얗고 찰지구나~  감수성 남다른 두부의 깨알 디테일 라이프","startDate":"20130408000000","restartDate":"20160905000000","serviceStatus":"service","viewerType":"scroll","weekTerm":"weekly","articleId":0,"media":"daum","payYn":"N","payType":"free","price":0,"ageGrade":0,"restYn":"N","monopolize":"N","dateCreated":"20130408161505","webtoonComment":{"id":0,"articleId":940,"commentUseYn":"N"},"cartoon":{"id":45467,"genres":[{"id":10,"name":"일상"},{"id":6,"name":"코믹"}],"artists":[{"id":17582,"name":"백두부","penName":"백두부","pictureImage":{"id":53520536,"url":"http://i1.cartoon.daumcdn.net/svc/image/U03/cartoon/563036910651CA0002","width":0,"height":0,"serviceStatus":"service"},"appImage":{"id":45408141,"url":"http://i1.cartoon.daumcdn.net/svc/image/U03/cartoon/51BEA8FA01559C0006","width":0,"height":0,"serviceStatus":"service"},"nameImage":{"id":44341931,"url":"http://i1.cartoon.daumcdn.net/svc/image/U03/cartoon/51626C640572E40002","width":0,"height":0,"serviceStatus":"service"},"birthDay":"20130408000000","debutDay":"20130408000000","email":"beancurd_i@naver.com","teamYn":"N","artistOrder":1,"artistType":"picture"},{"id":17582,"name":"백두부","penName":"백두부","pictureImage":{"id":53520536,"url":"http://i1.cartoon.daumcdn.net/svc/image/U03/cartoon/563036910651CA0002","width":0,"height":0,"serviceStatus":"service"},"appImage":{"id":45408141,"url":"http://i1.cartoon.daumcdn.net/svc/image/U03/cartoon/51BEA8FA01559C0006","width":0,"height":0,"serviceStatus":"service"},"nameImage":{"id":44341931,"url":"http://i1.cartoon.daumcdn.net/svc/image/U03/cartoon/51626C640572E40002","width":0,"height":0,"serviceStatus":"service"},"birthDay":"20130408000000","debutDay":"20130408000000","email":"beancurd_i@naver.com","teamYn":"N","artistOrder":1,"artistType":"story"}],"categories":[{"id":370,"name":"생활툰","categoryType":"keyword","priority":1},{"id":37,"name":"가족","categoryType":"keyword","priority":2},{"id":95,"name":"남매","categoryType":"keyword","priority":2},{"id":431,"name":"추억","categoryType":"keyword","priority":2},{"id":2,"name":"에피소드","categoryType":"story","priority":0}]},"webtoonWeeks":[{"id":19987,"weekDay":"tue"}],"latestWebtoonEpisode":{"id":46663,"episode":200,"title":"187화 안심이야","thumbnailImage":{"id":46663,"url":"http://t1.daumcdn.net/cartoon/5A26164A0254550001","width":0,"height":0,"serviceStatus":"service"},"episodeImage":{"id":0,"url":"http://t1.daumcdn.net/cartoon/5A26164C0408F80001","width":0,"height":0,"serviceStatus":"service"},"encryptUseYn":"N","serviceStatus":"service","articleId":0,"dateCreated":"20171212000100","price":0,"isTopRecommend":false,"isPaid":false,"ticketAvailable":false},"webtoonServices":[{"id":34748,"webtoonId":940,"serviceTarget":"series"},{"id":34749,"webtoonId":940,"serviceTarget":"padtoon"},{"id":34750,"webtoonId":940,"serviceTarget":"mobile"},{"id":34751,"webtoonId":940,"serviceTarget":"app"}],"score":0.0,"isNew":false,"averageScore":9.819088660122896,"ranking":0,"diff":0,"metricsScore":0,"sort":"desc","sortWeight":0},{"id":818,"nickname":"miseng","webtoonType":"series","title":"미생","finishYn":"N","titleImage2":{"id":0,"url":"http://t1.daumcdn.net/cartoon/587F0AF7053B1E0001","width":0,"height":0,"serviceStatus":"service"},"thumbnailImage":{"id":0,"url":"http://i1.cartoon.daumcdn.net/svc/image/U03/cartoon/4F14B5AF022F4A0001","width":0,"height":0,"serviceStatus":"service"},"thumbnailImage2":{"id":0,"url":"http://i1.cartoon.daumcdn.net/svc/image/U03/cartoon/5552FEB7053F890002","width":0,"height":0,"serviceStatus":"service"},"padThumbnailImage":{"id":0,"url":"http://i1.cartoon.daumcdn.net/svc/image/U03/cartoon/4F14B5BF057C770001","width":0,"height":0,"serviceStatus":"service"},"homeThumbnailImage":{"id":0,"url":"http://i1.cartoon.daumcdn.net/svc/image/U03/cartoon/4F14B5B60330F60001","width":0,"height":0,"serviceStatus":"service"},"appThumbnailImage":{"id":0,"url":"http://i1.cartoon.daumcdn.net/svc/image/U03/cartoon/5174C2040234E70002","width":0,"height":0,"serviceStatus":"service"},"pcThumbnailImage":{"id":0,"url":"http://i1.cartoon.daumcdn.net/svc/image/U03/cartoon/552622E8026BCD0003","width":0,"height":0,"serviceStatus":"service"},"pcRecommendImage":{"id":0,"url":"http://t1.daumcdn.net/webtoon/op/df793666ad673ace0c598fedbfb6a0179536d629","width":0,"height":0,"serviceStatus":"service"},"pcHomeImage":{"id":0,"url":"http://i1.cartoon.daumcdn.net/svc/image/U03/cartoon/5626BACC053A900001","width":0,"height":0,"serviceStatus":"service"},"pcHomeRightImage":{"id":0,"url":"http://i1.cartoon.daumcdn.net/svc/image/U03/cartoon/5626BAD4010FB00001","width":0,"height":0,"serviceStatus":"service"},"pcHomeLeftColor":"636363","pcHomeRightColor":"7d7d7d","introduction":"자신의 삶을 승리하기 위해 한 수 한 수 돌을 잇는 사람들의 이야기","startDate":"20120117000000","restartDate":"20170413000000","serviceStatus":"service","viewerType":"scroll","weekTerm":"weekly","articleId":0,"media":"daum","payYn":"Y","payType":"partial","price":200,"ageGrade":0,"restYn":"N","monopolize":"Y","dateCreated":"20120117084211","webtoonComment":{"id":0,"articleId":818,"commentUseYn":"Y"},"cartoon":{"id":40250,"genres":[{"id":2,"name":"드라마"}],"artists":[{"id":139,"name":"윤태호","penName":"윤태호","introduction":"\u003cp\u003e21세기 초입 한국만화의 유망신예로 지목되는 작가. \u0026lt;연씨별곡\u0026gt; 이후 \u0026lt;야후\u0026gt;, \u0026lt;수상한 아이들\u0026gt;로 잇대는 일련의 \u0026lsquo;화제작\u0026rsquo;으로 인기작가 대열에 성큼 진입하고 있다. 윤태호의 만화는 마치 독자의 의표(意表)를 찌르는 듯한 감각적인 글과 진지한 가운데서 시중일관 묻어나는 만화적 기발함 - 혹은 해학(諧謔)에서 찾아진다. 작가적 역량이 해를 더할수록 세련돼가고 있어 \u0026lsquo;문제작\u0026rsquo;을 터뜨리는 건 시간문제로 여겨지는 작가다.\u003c/p\u003e","history":"\u003cp\u003e1993년 비상착륙 \u003cbr /\u003e\r\n1996년 혼자사는 남편 \u003cbr /\u003e\r\n1997년 춘향별곡 \u003cbr /\u003e\r\n1998년 야후(YAHOO) \u003cbr /\u003e\r\n1999년 수상한 아이들 \u003cbr /\u003e\r\n2001년 로망스 \u003cbr /\u003e\r\n2007년 이끼\u003c/p\u003e","career":"\u003cp\u003e99년 오늘의 우리 만화상 \u003cbr /\u003e\r\n02년 대한민국 출판만화대상 저작상 \u003cbr /\u003e\r\n07년 대한민국 만화대상 우수상 \u003cbr /\u003e\r\n08년 부천만화상 일반만화상\u003c/p\u003e","smallPictureImage":{"id":58457,"url":"http://i1.cartoon.daumcdn.net/svc/image/U03/cartoon/U841ED144AB2B7E533","width":0,"height":0,"serviceStatus":"service"},"appImage":{"id":44856182,"url":"http://i1.cartoon.daumcdn.net/svc/image/U03/cartoon/519475B7011BDF0002","width":0,"height":0,"serviceStatus":"service"},"nameImage":{"id":6948095,"url":"http://i1.cartoon.daumcdn.net/svc/image/U03/cartoon/U744C0049A96D7377F","width":0,"height":0,"serviceStatus":"service"},"birthDay":"19690918000000","debutDay":"19930918000000","email":"taio69@hanmail.net","homepage":"","teamYn":"N","artistOrder":0,"artistType":"picture"},{"id":139,"name":"윤태호","penName":"윤태호","introduction":"\u003cp\u003e21세기 초입 한국만화의 유망신예로 지목되는 작가. \u0026lt;연씨별곡\u0026gt; 이후 \u0026lt;야후\u0026gt;, \u0026lt;수상한 아이들\u0026gt;로 잇대는 일련의 \u0026lsquo;화제작\u0026rsquo;으로 인기작가 대열에 성큼 진입하고 있다. 윤태호의 만화는 마치 독자의 의표(意表)를 찌르는 듯한 감각적인 글과 진지한 가운데서 시중일관 묻어나는 만화적 기발함 - 혹은 해학(諧謔)에서 찾아진다. 작가적 역량이 해를 더할수록 세련돼가고 있어 \u0026lsquo;문제작\u0026rsquo;을 터뜨리는 건 시간문제로 여겨지는 작가다.\u003c/p\u003e","history":"\u003cp\u003e1993년 비상착륙 \u003cbr /\u003e\r\n1996년 혼자사는 남편 \u003cbr /\u003e\r\n1997년 춘향별곡 \u003cbr /\u003e\r\n1998년 야후(YAHOO) \u003cbr /\u003e\r\n1999년 수상한 아이들 \u003cbr /\u003e\r\n2001년 로망스 \u003cbr /\u003e\r\n2007년 이끼\u003c/p\u003e","career":"\u003cp\u003e99년 오늘의 우리 만화상 \u003cbr /\u003e\r\n02년 대한민국 출판만화대상 저작상 \u003cbr /\u003e\r\n07년 대한민국 만화대상 우수상 \u003cbr /\u003e\r\n08년 부천만화상 일반만화상\u003c/p\u003e","smallPictureImage":{"id":58457,"url":"http://i1.cartoon.daumcdn.net/svc/image/U03/cartoon/U841ED144AB2B7E533","width":0,"height":0,"serviceStatus":"service"},"appImage":{"id":44856182,"url":"http://i1.cartoon.daumcdn.net/svc/image/U03/cartoon/519475B7011BDF0002","width":0,"height":0,"serviceStatus":"service"},"nameImage":{"id":6948095,"url":"http://i1.cartoon.daumcdn.net/svc/image/U03/cartoon/U744C0049A96D7377F","width":0,"height":0,"serviceStatus":"service"},"birthDay":"19690918000000","debutDay":"19930918000000","email":"taio69@hanmail.net","homepage":"","teamYn":"N","artistOrder":0,"artistType":"story"}],"categories":[{"id":414,"name":"직장생활","categoryType":"keyword","priority":1},{"id":222,"name":"사회초년생","categoryType":"keyword","priority":2},{"id":177,"name":"바둑","categoryType":"keyword","priority":2},{"id":1,"name":"스토리","categoryType":"story","priority":1}]},"webtoonWeeks":[{"id":19813,"weekDay":"tue"}],"latestWebtoonEpisode":{"id":46790,"episode":234,"title":"[part2] 제70수","thumbnailImage":{"id":46790,"url":"http://t1.daumcdn.net/cartoon/5A2E500B0347120001","width":0,"height":0,"serviceStatus":"service"},"encryptUseYn":"N","serviceStatus":"service","articleId":0,"dateCreated":"20171212000000","price":0,"isTopRecommend":false,"isPaid":false,"ticketAvailable":false},"webtoonServices":[{"id":34096,"webtoonId":818,"serviceTarget":"series"},{"id":34097,"webtoonId":818,"serviceTarget":"mobile"},{"id":34098,"webtoonId":818,"serviceTarget":"app"}],"score":0.0,"isNew":false,"averageScore":9.81319004464405,"ranking":0,"diff":0,"metricsScore":0,"sort":"desc","sortWeight":0}]}
